flask_includes_captcha/__init__.py
flask_includes_captcha/flask_includes_captcha.py
flask_includes_captcha-0.1.1.dist-info/LICENSE
flask_includes_captcha-0.1.1.dist-info/METADATA
flask_includes_captcha-0.1.1.dist-info/WHEEL
flask_includes_captcha-0.1.1.dist-info/top_level.txt
flask_includes_captcha-0.1.1.dist-info/RECORD
