Metadata-Version: 2.1
Name: flask-includes-captcha
Version: 0.1.1
Summary: A simple, limited (basic) wrap of the popular Captcha library for Flask projects.
Author-email: Martin Heisler <stripedkitefish@gmail.com>
Project-URL: Homepage, https://github.com/zfish85/flask-includes-captcha
Classifier: Development Status :: 3 - Alpha
Classifier: Environment :: Web Environment
Classifier: Framework :: Flask
Classifier: Intended Audience :: Developers
Classifier: License :: OSI Approved :: MIT License
Classifier: Programming Language :: Python
Classifier: Topic :: Internet
License-File: LICENSE
Requires-Dist: captcha >=0.5.0
Requires-Dist: pyjwt >=2.8.0
Requires-Dist: flask
Requires-Dist: flask-wtf
Requires-Dist: joserfc
